[{"line":2,"elements":[{"line":4,"name":"","description":"","type":"background","keyword":"Background","steps":[{"result":{"duration":1696059800,"status":"passed"},"line":5,"name":"The user sets up functions","match":{"location":"stepDefinitions.UIStepDefinitions.UIStepDefinitions.theUserSetsUpFunctions()"},"keyword":"Given "},{"result":{"duration":1015361100,"status":"passed"},"line":6,"name":"The user go to the \"baseURL\" website","match":{"arguments":[{"val":"\"baseURL\"","offset":19}],"location":"stepDefinitions.UIStepDefinitions.UIStepDefinitions.theUserGoToTheWebsite(java.lang.String)"},"keyword":"Given "}]},{"start_timestamp":"2024-03-12T13:36:42.097Z","line":8,"name":"Verify Homescreen","description":"","id":"verfiy-teststation-numer;verify-homescreen","after":[{"result":{"duration":116553100,"status":"passed"},"match":{"location":"stepDefinitions.Hooks.Hooks.tearDown(io.cucumber.java.Scenario)"}}],"type":"scenario","keyword":"Scenario","steps":[{"result":{"duration":2094137300,"status":"passed"},"line":10,"name":"The user asserts that \"ChargePointInstallationForm_HeaderText\" is visible","match":{"arguments":[{"val":"\"ChargePointInstallationForm_HeaderText\"","offset":22}],"location":"stepDefinitions.UIStepDefinitions.UIStepDefinitions.theUserAssertsThatIsVisible(java.lang.String)"},"keyword":"When "},{"result":{"duration":2056472800,"status":"passed"},"line":11,"name":"The user asserts that \"SerialNumberText\" is visible","match":{"arguments":[{"val":"\"SerialNumberText\"","offset":22}],"location":"stepDefinitions.UIStepDefinitions.UIStepDefinitions.theUserAssertsThatIsVisible(java.lang.String)"},"keyword":"Then "},{"result":{"duration":1097589600,"status":"passed"},"line":12,"name":"The user fills the \"InputSerialNumber\" box as \"TT 00 000\"","match":{"arguments":[{"val":"\"InputSerialNumber\"","offset":19},{"val":"\"TT 00 000\"","offset":46}],"location":"stepDefinitions.UIStepDefinitions.UIStepDefinitions.theUserFillsTheBoxAs(java.lang.String,java.lang.String)"},"keyword":"And "},{"result":{"duration":2035991100,"status":"passed"},"line":13,"name":"The user asserts that \"AddButton\" is visible","match":{"arguments":[{"val":"\"AddButton\"","offset":22}],"location":"stepDefinitions.UIStepDefinitions.UIStepDefinitions.theUserAssertsThatIsVisible(java.lang.String)"},"keyword":"When "},{"result":{"duration":2077961500,"status":"passed"},"line":14,"name":"The user clicks the \"AddButton\" button","match":{"arguments":[{"val":"\"AddButton\"","offset":20}],"location":"stepDefinitions.UIStepDefinitions.UIStepDefinitions.theUserClicksTheButton(java.lang.String)"},"keyword":"When "},{"result":{"duration":2080912600,"status":"passed"},"line":15,"name":"The user asserts that \"cancelButton\" is visible","match":{"arguments":[{"val":"\"cancelButton\"","offset":22}],"location":"stepDefinitions.UIStepDefinitions.UIStepDefinitions.theUserAssertsThatIsVisible(java.lang.String)"},"keyword":"Then "},{"result":{"duration":2082738400,"status":"passed"},"line":16,"name":"The user clicks the \"cancelButton\" button","match":{"arguments":[{"val":"\"cancelButton\"","offset":20}],"location":"stepDefinitions.UIStepDefinitions.UIStepDefinitions.theUserClicksTheButton(java.lang.String)"},"keyword":"When "}],"tags":[{"name":"@UI"},{"name":"@1"}]},{"line":4,"name":"","description":"","type":"background","keyword":"Background","steps":[{"result":{"duration":1011195400,"status":"passed"},"line":5,"name":"The user sets up functions","match":{"location":"stepDefinitions.UIStepDefinitions.UIStepDefinitions.theUserSetsUpFunctions()"},"keyword":"Given "},{"result":{"duration":2017976800,"status":"passed"},"line":6,"name":"The user go to the \"baseURL\" website","match":{"arguments":[{"val":"\"baseURL\"","offset":19}],"location":"stepDefinitions.UIStepDefinitions.UIStepDefinitions.theUserGoToTheWebsite(java.lang.String)"},"keyword":"Given "}]},{"start_timestamp":"2024-03-12T13:36:58.483Z","line":18,"name":"Verify The TestStation Functinality","description":"","id":"verfiy-teststation-numer;verify-the-teststation-functinality","after":[{"result":{"duration":79951900,"status":"passed"},"match":{"location":"stepDefinitions.Hooks.Hooks.tearDown(io.cucumber.java.Scenario)"}}],"type":"scenario","keyword":"Scenario","steps":[{"result":{"duration":1138956600,"status":"passed"},"line":19,"name":"The user fills the \"InputSerialNumber\" box as \"TT 00 000\"","match":{"arguments":[{"val":"\"InputSerialNumber\"","offset":19},{"val":"\"TT 00 000\"","offset":46}],"location":"stepDefinitions.UIStepDefinitions.UIStepDefinitions.theUserFillsTheBoxAs(java.lang.String,java.lang.String)"},"keyword":"When "},{"result":{"duration":2097715400,"status":"passed"},"line":20,"name":"The user clicks the \"AddButton\" button","match":{"arguments":[{"val":"\"AddButton\"","offset":20}],"location":"stepDefinitions.UIStepDefinitions.UIStepDefinitions.theUserClicksTheButton(java.lang.String)"},"keyword":"And "},{"result":{"duration":2047338800,"status":"passed"},"line":21,"name":"The user asserts that \"VerifyTestStationNumber\" is visible","match":{"arguments":[{"val":"\"VerifyTestStationNumber\"","offset":22}],"location":"stepDefinitions.UIStepDefinitions.UIStepDefinitions.theUserAssertsThatIsVisible(java.lang.String)"},"keyword":"Then "},{"result":{"duration":2054755400,"status":"passed"},"line":22,"name":"The user asserts that \"cancelButton\" is visible","match":{"arguments":[{"val":"\"cancelButton\"","offset":22}],"location":"stepDefinitions.UIStepDefinitions.UIStepDefinitions.theUserAssertsThatIsVisible(java.lang.String)"},"keyword":"And "},{"result":{"duration":2059193900,"status":"passed"},"line":23,"name":"The user clicks the \"cancelButton\" button","match":{"arguments":[{"val":"\"cancelButton\"","offset":20}],"location":"stepDefinitions.UIStepDefinitions.UIStepDefinitions.theUserClicksTheButton(java.lang.String)"},"keyword":"When "},{"result":{"duration":25013098200,"status":"passed"},"line":24,"name":"The user asserts that VerifyTestStationNumber is not visible","match":{"location":"stepDefinitions.UIStepDefinitions.UIStepDefinitions.the_user_asserts_that_verify_test_station_number_is_not_visible()"},"keyword":"Then "},{"result":{"duration":25022713600,"status":"passed"},"line":25,"name":"The user asserts that cancelButton is not visible","match":{"location":"stepDefinitions.UIStepDefinitions.UIStepDefinitions.the_user_asserts_that_cancel_button_is_not_visible()"},"keyword":"And "}],"tags":[{"name":"@UI"},{"name":"@1"}]}],"name":"verfiy TestStation Numer","description":"","id":"verfiy-teststation-numer","keyword":"Feature","uri":"file:src/test/resources/features/01_UIFeatures/US1_HomePageVerfication.feature","tags":[{"name":"@UI","type":"Tag","location":{"line":1,"column":1}},{"name":"@1","type":"Tag","location":{"line":1,"column":5}}]}]